pypeul.py
pypeul-0.3.2.dist-info/COPYING
pypeul-0.3.2.dist-info/WHEEL
pypeul-0.3.2.dist-info/METADATA
pypeul-0.3.2.dist-info/RECORD
